package/__init__.py
package/main.py
ixi_drag_n_drop-1.0.0.dist-info/LICENSE
ixi_drag_n_drop-1.0.0.dist-info/METADATA
ixi_drag_n_drop-1.0.0.dist-info/WHEEL
ixi_drag_n_drop-1.0.0.dist-info/top_level.txt
ixi_drag_n_drop-1.0.0.dist-info/RECORD
