Metadata-Version: 2.1
Name: ixi-drag-n-drop
Version: 1.0.0
Summary: 13
Author: ixslea
Classifier: Programming Language :: Python :: 3.11
Classifier: License :: OSI Approved :: MIT License
Requires-Python: >=3.7
License-File: LICENSE
Requires-Dist: Pillow>=11.0.0
Requires-Dist: tkinterdnd2>=0.4.2
